{
  "case_id": "toolox-44-t1-w8-e0.95",
  "layout_outcomes": [
    {
      "instance_id": "test-tight-clearance-0000",
      "minimum_safety_factor": 3.877153672106026,
      "report_count": 4,
      "reports": [
        {
          "cumulative_mesh_efficiency": 1.0,
          "fillet_radius_mm": 0.748849329536819,
          "max_von_mises_mpa": 59.68813267876502,
          "member": 0,
          "mesh_element_count": 240,
          "model_version": "involute-tooth-root-plane-stress-v3",
          "pressure_angle_deg": 20.0,
          "radial_force_n": 27.731065467901132,
          "root_width_mm": 2.9742521758107205,
          "safety_factor": 12.844540987616123,
          "section_height_mm": 2.7106065997240147,
          "stage_id": "input",
          "tangential_force_n": 76.19047619047619,
          "tooth_count": 21,
          "transmitted_torque_nm": 1.0
        },
        {
          "cumulative_mesh_efficiency": 0.95,
          "fillet_radius_mm": 0.375,
          "max_von_mises_mpa": 101.267530441901,
          "member": 0,
          "mesh_element_count": 240,
          "model_version": "involute-tooth-root-plane-stress-v3",
          "pressure_angle_deg": 20.0,
          "radial_force_n": 26.344512194506073,
          "root_width_mm": 1.894691898374343,
          "safety_factor": 7.570705667662322,
          "section_height_mm": 3.091744457185296,
          "stage_id": "compound",
          "tangential_force_n": 72.38095238095238,
          "tooth_count": 40,
          "transmitted_torque_nm": 1.8095238095238093
        },
        {
          "cumulative_mesh_efficiency": 0.95,
          "fillet_radius_mm": 0.7126591720692375,
          "max_von_mises_mpa": 111.13110491696489,
          "member": 1,
          "mesh_element_count": 240,
          "model_version": "involute-tooth-root-plane-stress-v3",
          "pressure_angle_deg": 20.0,
          "radial_force_n": 47.89911308092013,
          "root_width_mm": 2.8844716587272226,
          "safety_factor": 6.898758608037829,
          "section_height_mm": 2.716186916310045,
          "stage_id": "compound",
          "tangential_force_n": 131.6017316017316,
          "tooth_count": 22,
          "transmitted_torque_nm": 1.8095238095238093
        },
        {
          "cumulative_mesh_efficiency": 0.9025,
          "fillet_radius_mm": 0.375,
          "max_von_mises_mpa": 197.73956141651254,
          "member": 0,
          "mesh_element_count": 240,
          "model_version": "involute-tooth-root-plane-stress-v3",
          "pressure_angle_deg": 20.0,
          "radial_force_n": 45.50415742687413,
          "root_width_mm": 1.8221067318076687,
          "safety_factor": 3.877153672106026,
          "section_height_mm": 3.15184468916042,
          "stage_id": "output",
          "tangential_force_n": 125.02164502164503,
          "tooth_count": 46,
          "transmitted_torque_nm": 3.5943722943722944
        }
      ],
      "valid": true
    },
    {
      "instance_id": "train-procedural-0003",
      "minimum_safety_factor": 19.106372046155336,
      "report_count": 4,
      "reports": [
        {
          "cumulative_mesh_efficiency": 1.0,
          "fillet_radius_mm": 0.9418595254198188,
          "max_von_mises_mpa": 40.12622934456772,
          "member": 0,
          "mesh_element_count": 240,
          "model_version": "involute-tooth-root-plane-stress-v3",
          "pressure_angle_deg": 20.0,
          "radial_force_n": 24.264682284413492,
          "root_width_mm": 3.67644094002463,
          "safety_factor": 19.106372046155336,
          "section_height_mm": 3.2452429186502663,
          "stage_id": "input",
          "tangential_force_n": 66.66666666666667,
          "tooth_count": 20,
          "transmitted_torque_nm": 1.0
        },
        {
          "cumulative_mesh_efficiency": 0.95,
          "fillet_radius_mm": 0.9418595254198188,
          "max_von_mises_mpa": 38.11991787733927,
          "member": 0,
          "mesh_element_count": 240,
          "model_version": "involute-tooth-root-plane-stress-v3",
          "pressure_angle_deg": 20.0,
          "radial_force_n": 23.051448170192817,
          "root_width_mm": 3.67644094002463,
          "safety_factor": 20.111970574900386,
          "section_height_mm": 3.2452429186502663,
          "stage_id": "compound",
          "tangential_force_n": 63.333333333333336,
          "tooth_count": 20,
          "transmitted_torque_nm": 0.95
        },
        {
          "cumulative_mesh_efficiency": 0.95,
          "fillet_radius_mm": 0.19157510789298726,
          "max_von_mises_mpa": 38.44452851556018,
          "member": 1,
          "mesh_element_count": 240,
          "model_version": "involute-tooth-root-plane-stress-v3",
          "pressure_angle_deg": 20.0,
          "radial_force_n": 12.46024225415828,
          "root_width_mm": 1.8197596049069544,
          "safety_factor": 19.942152921874516,
          "section_height_mm": 3.31217691787878,
          "stage_id": "compound",
          "tangential_force_n": 34.234234234234236,
          "tooth_count": 37,
          "transmitted_torque_nm": 0.95
        },
        {
          "cumulative_mesh_efficiency": 0.9025,
          "fillet_radius_mm": 0.1468846162280144,
          "max_von_mises_mpa": 35.99155010264606,
          "member": 0,
          "mesh_element_count": 240,
          "model_version": "involute-tooth-root-plane-stress-v3",
          "pressure_angle_deg": 20.0,
          "radial_force_n": 11.83723014145036,
          "root_width_mm": 1.7093871993789755,
          "safety_factor": 21.30129612312258,
          "section_height_mm": 3.3140571092785684,
          "stage_id": "output",
          "tangential_force_n": 32.522522522522515,
          "tooth_count": 38,
          "transmitted_torque_nm": 0.9268918918918918
        }
      ],
      "valid": true
    },
    {
      "instance_id": "train-procedural-0000",
      "minimum_safety_factor": 11.231942799444733,
      "report_count": 4,
      "reports": [
        {
          "cumulative_mesh_efficiency": 1.0,
          "fillet_radius_mm": 0.8986191954441836,
          "max_von_mises_mpa": 41.45009213803286,
          "member": 0,
          "mesh_element_count": 240,
          "model_version": "involute-tooth-root-plane-stress-v3",
          "pressure_angle_deg": 20.0,
          "radial_force_n": 23.109221223250945,
          "root_width_mm": 3.569102610972866,
          "safety_factor": 18.496139022166506,
          "section_height_mm": 3.2527279196688177,
          "stage_id": "input",
          "tangential_force_n": 63.492063492063494,
          "tooth_count": 21,
          "transmitted_torque_nm": 1.0
        },
        {
          "cumulative_mesh_efficiency": 0.95,
          "fillet_radius_mm": 0.23623125690146551,
          "max_von_mises_mpa": 68.25770753609677,
          "member": 0,
          "mesh_element_count": 240,
          "model_version": "involute-tooth-root-plane-stress-v3",
          "pressure_angle_deg": 20.0,
          "radial_force_n": 21.953760162088393,
          "root_width_mm": 1.9300614309700572,
          "safety_factor": 11.231942799444733,
          "section_height_mm": 3.3101794688274104,
          "stage_id": "compound",
          "tangential_force_n": 60.31746031746031,
          "tooth_count": 36,
          "transmitted_torque_nm": 1.6285714285714283
        },
        {
          "cumulative_mesh_efficiency": 0.95,
          "fillet_radius_mm": 0.23623125690146551,
          "max_von_mises_mpa": 68.25770753609677,
          "member": 1,
          "mesh_element_count": 240,
          "model_version": "involute-tooth-root-plane-stress-v3",
          "pressure_angle_deg": 20.0,
          "radial_force_n": 21.953760162088393,
          "root_width_mm": 1.9300614309700572,
          "safety_factor": 11.231942799444733,
          "section_height_mm": 3.3101794688274104,
          "stage_id": "compound",
          "tangential_force_n": 60.31746031746031,
          "tooth_count": 36,
          "transmitted_torque_nm": 1.6285714285714283
        },
        {
          "cumulative_mesh_efficiency": 0.9025,
          "fillet_radius_mm": 0.44999999999999996,
          "max_von_mises_mpa": 66.80844022209293,
          "member": 0,
          "mesh_element_count": 240,
          "model_version": "involute-tooth-root-plane-stress-v3",
          "pressure_angle_deg": 20.0,
          "radial_force_n": 20.856072153983977,
          "root_width_mm": 2.2736302780492115,
          "safety_factor": 11.475595959403003,
          "section_height_mm": 3.7100933486223546,
          "stage_id": "output",
          "tangential_force_n": 57.301587301587304,
          "tooth_count": 40,
          "transmitted_torque_nm": 1.719047619047619
        }
      ],
      "valid": true
    },
    {
      "instance_id": "train-procedural-0002",
      "minimum_safety_factor": 8.786780386097556,
      "report_count": 4,
      "reports": [
        {
          "cumulative_mesh_efficiency": 1.0,
          "fillet_radius_mm": 0.48266963137664654,
          "max_von_mises_mpa": 87.25228502122195,
          "member": 0,
          "mesh_element_count": 240,
          "model_version": "involute-tooth-root-plane-stress-v3",
          "pressure_angle_deg": 20.0,
          "radial_force_n": 29.117618741296187,
          "root_width_mm": 2.0908354904543756,
          "safety_factor": 8.786780386097556,
          "section_height_mm": 2.183892290428231,
          "stage_id": "input",
          "tangential_force_n": 80.0,
          "tooth_count": 25,
          "transmitted_torque_nm": 1.0
        },
        {
          "cumulative_mesh_efficiency": 0.95,
          "fillet_radius_mm": 0.48266963137664654,
          "max_von_mises_mpa": 82.88967077016092,
          "member": 0,
          "mesh_element_count": 240,
          "model_version": "involute-tooth-root-plane-stress-v3",
          "pressure_angle_deg": 20.0,
          "radial_force_n": 27.66173780423138,
          "root_width_mm": 2.0908354904543756,
          "safety_factor": 9.249242511681631,
          "section_height_mm": 2.183892290428231,
          "stage_id": "compound",
          "tangential_force_n": 76.0,
          "tooth_count": 25,
          "transmitted_torque_nm": 0.95
        },
        {
          "cumulative_mesh_efficiency": 0.95,
          "fillet_radius_mm": 0.3,
          "max_von_mises_mpa": 80.84292015266608,
          "member": 1,
          "mesh_element_count": 240,
          "model_version": "involute-tooth-root-plane-stress-v3",
          "pressure_angle_deg": 20.0,
          "radial_force_n": 14.71369032139967,
          "root_width_mm": 1.4514996056746,
          "safety_factor": 9.48341135153049,
          "section_height_mm": 2.522098927161938,
          "stage_id": "compound",
          "tangential_force_n": 40.42553191489362,
          "tooth_count": 47,
          "transmitted_torque_nm": 0.95
        },
        {
          "cumulative_mesh_efficiency": 0.9025,
          "fillet_radius_mm": 0.3945352138143523,
          "max_von_mises_mpa": 49.858427209661016,
          "member": 0,
          "mesh_element_count": 240,
          "model_version": "involute-tooth-root-plane-stress-v3",
          "pressure_angle_deg": 20.0,
          "radial_force_n": 13.978005805329687,
          "root_width_mm": 1.8726744853071688,
          "safety_factor": 15.376872267605554,
          "section_height_mm": 2.192178396255148,
          "stage_id": "output",
          "tangential_force_n": 38.40425531914894,
          "tooth_count": 28,
          "transmitted_torque_nm": 0.5376595744680851
        }
      ],
      "valid": true
    },
    {
      "instance_id": "train-procedural-0001",
      "minimum_safety_factor": 8.91899759362617,
      "report_count": 4,
      "reports": [
        {
          "cumulative_mesh_efficiency": 1.0,
          "fillet_radius_mm": 0.3,
          "max_von_mises_mpa": 85.95883770778833,
          "member": 0,
          "mesh_element_count": 240,
          "model_version": "involute-tooth-root-plane-stress-v3",
          "pressure_angle_deg": 20.0,
          "radial_force_n": 15.824792794182711,
          "root_width_mm": 1.457685385446135,
          "safety_factor": 8.91899759362617,
          "section_height_mm": 2.5214757513283352,
          "stage_id": "input",
          "tangential_force_n": 43.47826086956522,
          "tooth_count": 46,
          "transmitted_torque_nm": 1.0
        },
        {
          "cumulative_mesh_efficiency": 0.95,
          "fillet_radius_mm": 0.5410662861939244,
          "max_von_mises_mpa": 46.17601784696594,
          "member": 0,
          "mesh_element_count": 240,
          "model_version": "involute-tooth-root-plane-stress-v3",
          "pressure_angle_deg": 20.0,
          "radial_force_n": 15.033553154473573,
          "root_width_mm": 2.2355227201024688,
          "safety_factor": 16.60313518605073,
          "section_height_mm": 2.1769652864909723,
          "stage_id": "compound",
          "tangential_force_n": 41.30434782608695,
          "tooth_count": 23,
          "transmitted_torque_nm": 0.475
        },
        {
          "cumulative_mesh_efficiency": 0.95,
          "fillet_radius_mm": 0.06810828179383677,
          "max_von_mises_mpa": 44.19495873950224,
          "member": 1,
          "mesh_element_count": 240,
          "model_version": "involute-tooth-root-plane-stress-v3",
          "pressure_angle_deg": 20.0,
          "radial_force_n": 8.865941603920312,
          "root_width_mm": 1.0659664750624027,
          "safety_factor": 17.347378265146027,
          "section_height_mm": 2.210553296628813,
          "stage_id": "compound",
          "tangential_force_n": 24.358974358974358,
          "tooth_count": 39,
          "transmitted_torque_nm": 0.475
        },
        {
          "cumulative_mesh_efficiency": 0.9025,
          "fillet_radius_mm": 0.3,
          "max_von_mises_mpa": 46.27738954893001,
          "member": 0,
          "mesh_element_count": 240,
          "model_version": "involute-tooth-root-plane-stress-v3",
          "pressure_angle_deg": 20.0,
          "radial_force_n": 8.422644523724298,
          "root_width_mm": 1.4514996056746,
          "safety_factor": 16.56676563089313,
          "section_height_mm": 2.522098927161938,
          "stage_id": "output",
          "tangential_force_n": 23.14102564102564,
          "tooth_count": 47,
          "transmitted_torque_nm": 0.5438141025641026
        }
      ],
      "valid": true
    },
    {
      "instance_id": "test-tight-clearance-0001",
      "minimum_safety_factor": 9.413227509523105,
      "report_count": 4,
      "reports": [
        {
          "cumulative_mesh_efficiency": 1.0,
          "fillet_radius_mm": 0.5666939071970472,
          "max_von_mises_mpa": 54.00785056324771,
          "member": 0,
          "mesh_element_count": 240,
          "model_version": "involute-tooth-root-plane-stress-v3",
          "pressure_angle_deg": 20.0,
          "radial_force_n": 22.398168262535528,
          "root_width_mm": 2.522810172332858,
          "safety_factor": 14.195467115819318,
          "section_height_mm": 2.7336231966223856,
          "stage_id": "input",
          "tangential_force_n": 61.53846153846154,
          "tooth_count": 26,
          "transmitted_torque_nm": 1.0
        },
        {
          "cumulative_mesh_efficiency": 0.95,
          "fillet_radius_mm": 0.6033370392208077,
          "max_von_mises_mpa": 51.00902816624842,
          "member": 0,
          "mesh_element_count": 240,
          "model_version": "involute-tooth-root-plane-stress-v3",
          "pressure_angle_deg": 20.0,
          "radial_force_n": 21.27825984940875,
          "root_width_mm": 2.6135443630679687,
          "safety_factor": 15.030019081483962,
          "section_height_mm": 2.7298653630352874,
          "stage_id": "compound",
          "tangential_force_n": 58.46153846153846,
          "tooth_count": 25,
          "transmitted_torque_nm": 0.9134615384615384
        },
        {
          "cumulative_mesh_efficiency": 0.95,
          "fillet_radius_mm": 0.8207353209682644,
          "max_von_mises_mpa": 52.86758621166429,
          "member": 1,
          "mesh_element_count": 240,
          "model_version": "involute-tooth-root-plane-stress-v3",
          "pressure_angle_deg": 20.0,
          "radial_force_n": 27.99771032816941,
          "root_width_mm": 3.152763796879679,
          "safety_factor": 14.50163931444094,
          "section_height_mm": 2.6973548666498175,
          "stage_id": "compound",
          "tangential_force_n": 76.92307692307692,
          "tooth_count": 19,
          "transmitted_torque_nm": 0.9134615384615384
        },
        {
          "cumulative_mesh_efficiency": 0.9025,
          "fillet_radius_mm": 0.45630370339355153,
          "max_von_mises_mpa": 81.44567481143432,
          "member": 0,
          "mesh_element_count": 240,
          "model_version": "involute-tooth-root-plane-stress-v3",
          "pressure_angle_deg": 20.0,
          "radial_force_n": 26.59782481176094,
          "root_width_mm": 2.2496451921349423,
          "safety_factor": 9.413227509523105,
          "section_height_mm": 2.7431352487912193,
          "stage_id": "output",
          "tangential_force_n": 73.07692307692308,
          "tooth_count": 29,
          "transmitted_torque_nm": 1.3245192307692308
        }
      ],
      "valid": true
    },
    {
      "instance_id": "train-procedural-0007",
      "minimum_safety_factor": 6.378001711689555,
      "report_count": 4,
      "reports": [
        {
          "cumulative_mesh_efficiency": 1.0,
          "fillet_radius_mm": 0.8207353209682644,
          "max_von_mises_mpa": 57.876094379085245,
          "member": 0,
          "mesh_element_count": 240,
          "model_version": "involute-tooth-root-plane-stress-v3",
          "pressure_angle_deg": 20.0,
          "radial_force_n": 30.650124990838094,
          "root_width_mm": 3.152763796879679,
          "safety_factor": 13.246689758383521,
          "section_height_mm": 2.6973548666498175,
          "stage_id": "input",
          "tangential_force_n": 84.21052631578948,
          "tooth_count": 19,
          "transmitted_torque_nm": 1.0
        },
        {
          "cumulative_mesh_efficiency": 0.95,
          "fillet_radius_mm": 0.5299682897569227,
          "max_von_mises_mpa": 76.57842502593473,
          "member": 0,
          "mesh_element_count": 240,
          "model_version": "involute-tooth-root-plane-stress-v3",
          "pressure_angle_deg": 20.0,
          "radial_force_n": 29.117618741296184,
          "root_width_mm": 2.4319034877485923,
          "safety_factor": 10.011523041992838,
          "section_height_mm": 2.7370630665751,
          "stage_id": "compound",
          "tangential_force_n": 79.99999999999999,
          "tooth_count": 27,
          "transmitted_torque_nm": 1.3499999999999999
        },
        {
          "cumulative_mesh_efficiency": 0.95,
          "fillet_radius_mm": 0.5299682897569227,
          "max_von_mises_mpa": 76.57842502593473,
          "member": 1,
          "mesh_element_count": 240,
          "model_version": "involute-tooth-root-plane-stress-v3",
          "pressure_angle_deg": 20.0,
          "radial_force_n": 29.117618741296184,
          "root_width_mm": 2.4319034877485923,
          "safety_factor": 10.011523041992838,
          "section_height_mm": 2.7370630665751,
          "stage_id": "compound",
          "tangential_force_n": 79.99999999999999,
          "tooth_count": 27,
          "transmitted_torque_nm": 1.3499999999999999
        },
        {
          "cumulative_mesh_efficiency": 0.9025,
          "fillet_radius_mm": 0.375,
          "max_von_mises_mpa": 120.20483865056443,
          "member": 0,
          "mesh_element_count": 240,
          "model_version": "involute-tooth-root-plane-stress-v3",
          "pressure_angle_deg": 20.0,
          "radial_force_n": 27.66173780423137,
          "root_width_mm": 1.8221067318076687,
          "safety_factor": 6.378001711689555,
          "section_height_mm": 3.15184468916042,
          "stage_id": "output",
          "tangential_force_n": 75.99999999999999,
          "tooth_count": 46,
          "transmitted_torque_nm": 2.1849999999999996
        }
      ],
      "valid": true
    },
    {
      "instance_id": "train-procedural-0004",
      "minimum_safety_factor": 31.834151699838564,
      "report_count": 4,
      "reports": [
        {
          "cumulative_mesh_efficiency": 1.0,
          "fillet_radius_mm": 0.37446682778409013,
          "max_von_mises_mpa": 24.08315050752725,
          "member": 0,
          "mesh_element_count": 240,
          "model_version": "involute-tooth-root-plane-stress-v3",
          "pressure_angle_deg": 20.0,
          "radial_force_n": 10.399149550462925,
          "root_width_mm": 2.7203820564121823,
          "safety_factor": 31.834151699838564,
          "section_height_mm": 4.410738159153517,
          "stage_id": "input",
          "tangential_force_n": 28.571428571428573,
          "tooth_count": 35,
          "transmitted_torque_nm": 1.0
        },
        {
          "cumulative_mesh_efficiency": 0.95,
          "fillet_radius_mm": 1.255812700559762,
          "max_von_mises_mpa": 12.252830746287023,
          "member": 0,
          "mesh_element_count": 240,
          "model_version": "involute-tooth-root-plane-stress-v3",
          "pressure_angle_deg": 20.0,
          "radial_force_n": 9.879192072939777,
          "root_width_mm": 4.901921253366181,
          "safety_factor": 62.570575121915375,
          "section_height_mm": 4.326990558200347,
          "stage_id": "compound",
          "tangential_force_n": 27.14285714285714,
          "tooth_count": 20,
          "transmitted_torque_nm": 0.5428571428571428
        },
        {
          "cumulative_mesh_efficiency": 0.95,
          "fillet_radius_mm": 0.43390454844372073,
          "max_von_mises_mpa": 12.40512013242118,
          "member": 1,
          "mesh_element_count": 240,
          "model_version": "involute-tooth-root-plane-stress-v3",
          "pressure_angle_deg": 20.0,
          "radial_force_n": 5.811289454670457,
          "root_width_mm": 2.867237428841292,
          "safety_factor": 61.80243790327823,
          "section_height_mm": 4.407715716392495,
          "stage_id": "compound",
          "tangential_force_n": 15.966386554621847,
          "tooth_count": 34,
          "transmitted_torque_nm": 0.5428571428571428
        },
        {
          "cumulative_mesh_efficiency": 0.9025,
          "fillet_radius_mm": 0.37446682778409013,
          "max_von_mises_mpa": 12.785319607672578,
          "member": 0,
          "mesh_element_count": 240,
          "model_version": "involute-tooth-root-plane-stress-v3",
          "pressure_angle_deg": 20.0,
          "radial_force_n": 5.520724981936935,
          "root_width_mm": 2.7203820564121823,
          "safety_factor": 59.964607080028216,
          "section_height_mm": 4.410738159153517,
          "stage_id": "output",
          "tangential_force_n": 15.168067226890756,
          "tooth_count": 35,
          "transmitted_torque_nm": 0.5308823529411765
        }
      ],
      "valid": true
    },
    {
      "instance_id": "train-procedural-0006",
      "minimum_safety_factor": 20.067744585659458,
      "report_count": 4,
      "reports": [
        {
          "cumulative_mesh_efficiency": 1.0,
          "fillet_radius_mm": 0.44999999999999996,
          "max_von_mises_mpa": 38.20392787012705,
          "member": 0,
          "mesh_element_count": 240,
          "model_version": "involute-tooth-root-plane-stress-v3",
          "pressure_angle_deg": 20.0,
          "radial_force_n": 10.549861862788473,
          "root_width_mm": 2.1865280781692022,
          "safety_factor": 20.067744585659458,
          "section_height_mm": 3.782213626992508,
          "stage_id": "input",
          "tangential_force_n": 28.985507246376812,
          "tooth_count": 46,
          "transmitted_torque_nm": 1.0
        },
        {
          "cumulative_mesh_efficiency": 0.95,
          "fillet_radius_mm": 0.44999999999999996,
          "max_von_mises_mpa": 33.299876885904986,
          "member": 0,
          "mesh_element_count": 240,
          "model_version": "involute-tooth-root-plane-stress-v3",
          "pressure_angle_deg": 20.0,
          "radial_force_n": 10.022368769649049,
          "root_width_mm": 2.252634363224348,
          "safety_factor": 23.023108142215914,
          "section_height_mm": 3.7564557216650982,
          "stage_id": "compound",
          "tangential_force_n": 27.536231884057965,
          "tooth_count": 41,
          "transmitted_torque_nm": 0.8467391304347824
        },
        {
          "cumulative_mesh_efficiency": 0.95,
          "fillet_radius_mm": 0.2808501208380676,
          "max_von_mises_mpa": 36.25270385577264,
          "member": 1,
          "mesh_element_count": 240,
          "model_version": "involute-tooth-root-plane-stress-v3",
          "pressure_angle_deg": 20.0,
          "radial_force_n": 11.740489130160313,
          "root_width_mm": 2.0402865423091368,
          "safety_factor": 21.147847887891754,
          "section_height_mm": 3.3080536193651326,
          "stage_id": "compound",
          "tangential_force_n": 32.2567287784679,
          "tooth_count": 35,
          "transmitted_torque_nm": 0.8467391304347824
        },
        {
          "cumulative_mesh_efficiency": 0.9025,
          "fillet_radius_mm": 0.9418595254198188,
          "max_von_mises_mpa": 18.444357780402036,
          "member": 0,
          "mesh_element_count": 240,
          "model_version": "involute-tooth-root-plane-stress-v3",
          "pressure_angle_deg": 20.0,
          "radial_force_n": 11.153464673652298,
          "root_width_mm": 3.67644094002463,
          "safety_factor": 41.56646036661058,
          "section_height_mm": 3.2452429186502663,
          "stage_id": "output",
          "tangential_force_n": 30.643892339544507,
          "tooth_count": 20,
          "transmitted_torque_nm": 0.45965838509316764
        }
      ],
      "valid": true
    },
    {
      "instance_id": "train-procedural-0005",
      "minimum_safety_factor": 32.80982272753414,
      "report_count": 4,
      "reports": [
        {
          "cumulative_mesh_efficiency": 1.0,
          "fillet_radius_mm": 0.43390454844372073,
          "max_von_mises_mpa": 22.851537086039052,
          "member": 0,
          "mesh_element_count": 240,
          "model_version": "involute-tooth-root-plane-stress-v3",
          "pressure_angle_deg": 20.0,
          "radial_force_n": 10.705006890182421,
          "root_width_mm": 2.867237428841292,
          "safety_factor": 33.549894861779556,
          "section_height_mm": 4.407715716392495,
          "stage_id": "input",
          "tangential_force_n": 29.41176470588235,
          "tooth_count": 34,
          "transmitted_torque_nm": 1.0
        },
        {
          "cumulative_mesh_efficiency": 0.95,
          "fillet_radius_mm": 0.49328325558212427,
          "max_von_mises_mpa": 19.856427755388655,
          "member": 0,
          "mesh_element_count": 240,
          "model_version": "involute-tooth-root-plane-stress-v3",
          "pressure_angle_deg": 20.0,
          "radial_force_n": 10.1697565456733,
          "root_width_mm": 3.0139710761548586,
          "safety_factor": 38.6105031635717,
          "section_height_mm": 4.40448628443351,
          "stage_id": "compound",
          "tangential_force_n": 27.941176470588232,
          "tooth_count": 33,
          "transmitted_torque_nm": 0.9220588235294117
        },
        {
          "cumulative_mesh_efficiency": 0.95,
          "fillet_radius_mm": 0.43390454844372073,
          "max_von_mises_mpa": 21.07046140139187,
          "member": 1,
          "mesh_element_count": 240,
          "model_version": "involute-tooth-root-plane-stress-v3",
          "pressure_angle_deg": 20.0,
          "radial_force_n": 9.87064605903585,
          "root_width_mm": 2.867237428841292,
          "safety_factor": 36.385850886778506,
          "section_height_mm": 4.407715716392495,
          "stage_id": "compound",
          "tangential_force_n": 27.119377162629757,
          "tooth_count": 34,
          "transmitted_torque_nm": 0.9220588235294117
        },
        {
          "cumulative_mesh_efficiency": 0.9025,
          "fillet_radius_mm": 0.6,
          "max_von_mises_mpa": 23.366985949097394,
          "member": 0,
          "mesh_element_count": 240,
          "model_version": "involute-tooth-root-plane-stress-v3",
          "pressure_angle_deg": 20.0,
          "radial_force_n": 9.377113756084059,
          "root_width_mm": 3.0035124842991308,
          "safety_factor": 32.80982272753414,
          "section_height_mm": 5.0086076288868,
          "stage_id": "output",
          "tangential_force_n": 25.76340830449827,
          "tooth_count": 41,
          "transmitted_torque_nm": 1.056299740484429
        }
      ],
      "valid": true
    },
    {
      "instance_id": "test-tight-clearance-0002",
      "minimum_safety_factor": 8.752075953520805,
      "report_count": 4,
      "reports": [
        {
          "cumulative_mesh_efficiency": 1.0,
          "fillet_radius_mm": 0.3,
          "max_von_mises_mpa": 87.59826477034288,
          "member": 0,
          "mesh_element_count": 240,
          "model_version": "involute-tooth-root-plane-stress-v3",
          "pressure_angle_deg": 20.0,
          "radial_force_n": 16.54410155755465,
          "root_width_mm": 1.471788534281056,
          "safety_factor": 8.752075953520805,
          "section_height_mm": 2.520153897589644,
          "stage_id": "input",
          "tangential_force_n": 45.45454545454545,
          "tooth_count": 44,
          "transmitted_torque_nm": 1.0
        },
        {
          "cumulative_mesh_efficiency": 0.95,
          "fillet_radius_mm": 0.627906350279881,
          "max_von_mises_mpa": 38.98627964727701,
          "member": 0,
          "mesh_element_count": 240,
          "model_version": "involute-tooth-root-plane-stress-v3",
          "pressure_angle_deg": 20.0,
          "radial_force_n": 15.716896479676915,
          "root_width_mm": 2.4509606266830906,
          "safety_factor": 19.665037895459058,
          "section_height_mm": 2.1634952791001734,
          "stage_id": "compound",
          "tangential_force_n": 43.18181818181817,
          "tooth_count": 20,
          "transmitted_torque_nm": 0.43181818181818177
        },
        {
          "cumulative_mesh_efficiency": 0.95,
          "fillet_radius_mm": 0.2762987097914156,
          "max_von_mises_mpa": 36.35871726760205,
          "member": 1,
          "mesh_element_count": 240,
          "model_version": "involute-tooth-root-plane-stress-v3",
          "pressure_angle_deg": 20.0,
          "radial_force_n": 9.823060299798072,
          "root_width_mm": 1.5802857056892479,
          "safety_factor": 21.086185770085343,
          "section_height_mm": 2.2005141167778888,
          "stage_id": "compound",
          "tangential_force_n": 26.98863636363636,
          "tooth_count": 32,
          "transmitted_torque_nm": 0.43181818181818177
        },
        {
          "cumulative_mesh_efficiency": 0.9025,
          "fillet_radius_mm": 0.3,
          "max_von_mises_mpa": 48.68494357237921,
          "member": 0,
          "mesh_element_count": 240,
          "model_version": "involute-tooth-root-plane-stress-v3",
          "pressure_angle_deg": 20.0,
          "radial_force_n": 9.33190728480817,
          "root_width_mm": 1.4800007590138549,
          "safety_factor": 15.747510634922977,
          "section_height_mm": 2.519454810180193,
          "stage_id": "output",
          "tangential_force_n": 25.63920454545454,
          "tooth_count": 43,
          "transmitted_torque_nm": 0.5512428977272726
        }
      ],
      "valid": true
    },
    {
      "instance_id": "train-procedural-0011",
      "minimum_safety_factor": 12.702792451750081,
      "report_count": 4,
      "reports": [
        {
          "cumulative_mesh_efficiency": 1.0,
          "fillet_radius_mm": 0.19685938075122067,
          "max_von_mises_mpa": 60.35418350561509,
          "member": 0,
          "mesh_element_count": 240,
          "model_version": "involute-tooth-root-plane-stress-v3",
          "pressure_angle_deg": 20.0,
          "radial_force_n": 16.176454856275658,
          "root_width_mm": 1.6083845258083798,
          "safety_factor": 12.702792451750081,
          "section_height_mm": 2.7584828906895105,
          "stage_id": "input",
          "tangential_force_n": 44.44444444444444,
          "tooth_count": 36,
          "transmitted_torque_nm": 1.0
        },
        {
          "cumulative_mesh_efficiency": 0.95,
          "fillet_radius_mm": 0.5666939071970472,
          "max_von_mises_mpa": 37.05538635867272,
          "member": 0,
          "mesh_element_count": 240,
          "model_version": "involute-tooth-root-plane-stress-v3",
          "pressure_angle_deg": 20.0,
          "radial_force_n": 15.367632113461877,
          "root_width_mm": 2.522810172332858,
          "safety_factor": 20.6897496424897,
          "section_height_mm": 2.7336231966223856,
          "stage_id": "compound",
          "tangential_force_n": 42.22222222222222,
          "tooth_count": 26,
          "transmitted_torque_nm": 0.6861111111111111
        },
        {
          "cumulative_mesh_efficiency": 0.95,
          "fillet_radius_mm": 0.375,
          "max_von_mises_mpa": 38.78163284206091,
          "member": 1,
          "mesh_element_count": 240,
          "model_version": "involute-tooth-root-plane-stress-v3",
          "pressure_angle_deg": 20.0,
          "radial_force_n": 9.29205662674439,
          "root_width_mm": 1.8500009487673188,
          "safety_factor": 19.76880833741411,
          "section_height_mm": 3.149318512725248,
          "stage_id": "compound",
          "tangential_force_n": 25.529715762273902,
          "tooth_count": 43,
          "transmitted_torque_nm": 0.6861111111111111
        },
        {
          "cumulative_mesh_efficiency": 0.9025,
          "fillet_radius_mm": 0.6033370392208077,
          "max_von_mises_mpa": 21.161497343904887,
          "member": 0,
          "mesh_element_count": 240,
          "model_version": "involute-tooth-root-plane-stress-v3",
          "pressure_angle_deg": 20.0,
          "radial_force_n": 8.827453795407171,
          "root_width_mm": 2.6135443630679687,
          "safety_factor": 36.22932036458604,
          "section_height_mm": 2.7298653630352874,
          "stage_id": "output",
          "tangential_force_n": 24.253229974160206,
          "tooth_count": 25,
          "transmitted_torque_nm": 0.3789567183462532
        }
      ],
      "valid": true
    },
    {
      "instance_id": "train-procedural-0008",
      "minimum_safety_factor": 19.39426668280978,
      "report_count": 4,
      "reports": [
        {
          "cumulative_mesh_efficiency": 1.0,
          "fillet_radius_mm": 0.44999999999999996,
          "max_von_mises_mpa": 39.53058288850932,
          "member": 0,
          "mesh_element_count": 240,
          "model_version": "involute-tooth-root-plane-stress-v3",
          "pressure_angle_deg": 20.0,
          "radial_force_n": 11.554610611625472,
          "root_width_mm": 2.234091901762518,
          "safety_factor": 19.39426668280978,
          "section_height_mm": 3.778098710718062,
          "stage_id": "input",
          "tangential_force_n": 31.746031746031747,
          "tooth_count": 42,
          "transmitted_torque_nm": 1.0
        },
        {
          "cumulative_mesh_efficiency": 0.95,
          "fillet_radius_mm": 0.8551910064830857,
          "max_von_mises_mpa": 21.222954064004277,
          "member": 0,
          "mesh_element_count": 240,
          "model_version": "involute-tooth-root-plane-stress-v3",
          "pressure_angle_deg": 20.0,
          "radial_force_n": 10.976880081044197,
          "root_width_mm": 3.461365990472668,
          "safety_factor": 36.124408711178944,
          "section_height_mm": 3.259424299572057,
          "stage_id": "compound",
          "tangential_force_n": 30.158730158730158,
          "tooth_count": 22,
          "transmitted_torque_nm": 0.49761904761904757
        },
        {
          "cumulative_mesh_efficiency": 0.95,
          "fillet_radius_mm": 0.44999999999999996,
          "max_von_mises_mpa": 19.37358448360533,
          "member": 1,
          "mesh_element_count": 240,
          "model_version": "involute-tooth-root-plane-stress-v3",
          "pressure_angle_deg": 20.0,
          "radial_force_n": 5.488440040522098,
          "root_width_mm": 2.207682801421584,
          "safety_factor": 39.57278361758245,
          "section_height_mm": 3.780230846384466,
          "stage_id": "compound",
          "tangential_force_n": 15.079365079365079,
          "tooth_count": 44,
          "transmitted_torque_nm": 0.49761904761904757
        },
        {
          "cumulative_mesh_efficiency": 0.9025,
          "fillet_radius_mm": 0.5475644440722611,
          "max_von_mises_mpa": 13.30494820001542,
          "member": 0,
          "mesh_element_count": 240,
          "model_version": "involute-tooth-root-plane-stress-v3",
          "pressure_angle_deg": 20.0,
          "radial_force_n": 5.214018038495994,
          "root_width_mm": 2.6995742305619292,
          "safety_factor": 57.62267204210371,
          "section_height_mm": 3.291762298549461,
          "stage_id": "output",
          "tangential_force_n": 14.325396825396826,
          "tooth_count": 29,
          "transmitted_torque_nm": 0.31157738095238097
        }
      ],
      "valid": true
    },
    {
      "instance_id": "train-procedural-0010",
      "minimum_safety_factor": 9.627379542381206,
      "report_count": 4,
      "reports": [
        {
          "cumulative_mesh_efficiency": 1.0,
          "fillet_radius_mm": 1.0276515992190145,
          "max_von_mises_mpa": 43.365758052523255,
          "member": 0,
          "mesh_element_count": 240,
          "model_version": "involute-tooth-root-plane-stress-v3",
          "pressure_angle_deg": 20.0,
          "radial_force_n": 26.960758093792766,
          "root_width_mm": 3.8896503716824107,
          "safety_factor": 17.679079095956396,
          "section_height_mm": 3.2272970776721195,
          "stage_id": "input",
          "tangential_force_n": 74.07407407407408,
          "tooth_count": 18,
          "transmitted_torque_nm": 1.0
        },
        {
          "cumulative_mesh_efficiency": 0.95,
          "fillet_radius_mm": 0.23623125690146551,
          "max_von_mises_mpa": 79.63399212544618,
          "member": 0,
          "mesh_element_count": 240,
          "model_version": "involute-tooth-root-plane-stress-v3",
          "pressure_angle_deg": 20.0,
          "radial_force_n": 25.612720189103126,
          "root_width_mm": 1.9300614309700572,
          "safety_factor": 9.627379542381206,
          "section_height_mm": 3.3101794688274104,
          "stage_id": "compound",
          "tangential_force_n": 70.37037037037037,
          "tooth_count": 36,
          "transmitted_torque_nm": 1.9
        },
        {
          "cumulative_mesh_efficiency": 0.95,
          "fillet_radius_mm": 0.23623125690146551,
          "max_von_mises_mpa": 79.63399212544618,
          "member": 1,
          "mesh_element_count": 240,
          "model_version": "involute-tooth-root-plane-stress-v3",
          "pressure_angle_deg": 20.0,
          "radial_force_n": 25.612720189103126,
          "root_width_mm": 1.9300614309700572,
          "safety_factor": 9.627379542381206,
          "section_height_mm": 3.3101794688274104,
          "stage_id": "compound",
          "tangential_force_n": 70.37037037037037,
          "tooth_count": 36,
          "transmitted_torque_nm": 1.9
        },
        {
          "cumulative_mesh_efficiency": 0.9025,
          "fillet_radius_mm": 0.2808501208380676,
          "max_von_mises_mpa": 75.13348312656417,
          "member": 0,
          "mesh_element_count": 240,
          "model_version": "involute-tooth-root-plane-stress-v3",
          "pressure_angle_deg": 20.0,
          "radial_force_n": 24.332084179647975,
          "root_width_mm": 2.0402865423091368,
          "safety_factor": 10.204061288829084,
          "section_height_mm": 3.3080536193651326,
          "stage_id": "output",
          "tangential_force_n": 66.85185185185186,
          "tooth_count": 35,
          "transmitted_torque_nm": 1.7548611111111112
        }
      ],
      "valid": true
    },
    {
      "instance_id": "train-procedural-0009",
      "minimum_safety_factor": 11.570156865532796,
      "report_count": 4,
      "reports": [
        {
          "cumulative_mesh_efficiency": 1.0,
          "fillet_radius_mm": 0.5666939071970472,
          "max_von_mises_mpa": 54.00785056324771,
          "member": 0,
          "mesh_element_count": 240,
          "model_version": "involute-tooth-root-plane-stress-v3",
          "pressure_angle_deg": 20.0,
          "radial_force_n": 22.398168262535528,
          "root_width_mm": 2.522810172332858,
          "safety_factor": 14.195467115819318,
          "section_height_mm": 2.7336231966223856,
          "stage_id": "input",
          "tangential_force_n": 61.53846153846154,
          "tooth_count": 26,
          "transmitted_torque_nm": 1.0
        },
        {
          "cumulative_mesh_efficiency": 0.95,
          "fillet_radius_mm": 0.3824004986684919,
          "max_von_mises_mpa": 64.18867223108606,
          "member": 0,
          "mesh_element_count": 240,
          "model_version": "involute-tooth-root-plane-stress-v3",
          "pressure_angle_deg": 20.0,
          "radial_force_n": 21.27825984940875,
          "root_width_mm": 2.0668908308863125,
          "safety_factor": 11.943955841719003,
          "section_height_mm": 2.7483230346897294,
          "stage_id": "compound",
          "tangential_force_n": 58.46153846153846,
          "tooth_count": 31,
          "transmitted_torque_nm": 1.1326923076923077
        },
        {
          "cumulative_mesh_efficiency": 0.95,
          "fillet_radius_mm": 0.27119034277732723,
          "max_von_mises_mpa": 66.26242630733445,
          "member": 1,
          "mesh_element_count": 240,
          "model_version": "involute-tooth-root-plane-stress-v3",
          "pressure_angle_deg": 20.0,
          "radial_force_n": 19.400766333284448,
          "root_width_mm": 1.7920233930258112,
          "safety_factor": 11.570156865532796,
          "section_height_mm": 2.7548223227453086,
          "stage_id": "compound",
          "tangential_force_n": 53.303167420814475,
          "tooth_count": 34,
          "transmitted_torque_nm": 1.1326923076923077
        },
        {
          "cumulative_mesh_efficiency": 0.9025,
          "fillet_radius_mm": 0.3824004986684919,
          "max_von_mises_mpa": 55.59871756486731,
          "member": 0,
          "mesh_element_count": 240,
          "model_version": "involute-tooth-root-plane-stress-v3",
          "pressure_angle_deg": 20.0,
          "radial_force_n": 18.43072801662023,
          "root_width_mm": 2.0668908308863125,
          "safety_factor": 13.78928688008303,
          "section_height_mm": 2.7483230346897294,
          "stage_id": "output",
          "tangential_force_n": 50.63800904977376,
          "tooth_count": 31,
          "transmitted_torque_nm": 0.9811114253393666
        }
      ],
      "valid": true
    },
    {
      "instance_id": "test-tight-clearance-0003",
      "minimum_safety_factor": 33.68008049028071,
      "report_count": 4,
      "reports": [
        {
          "cumulative_mesh_efficiency": 1.0,
          "fillet_radius_mm": 0.2554334771906497,
          "max_von_mises_mpa": 22.763207673684416,
          "member": 0,
          "mesh_element_count": 240,
          "model_version": "involute-tooth-root-plane-stress-v3",
          "pressure_angle_deg": 20.0,
          "radial_force_n": 9.837033358546009,
          "root_width_mm": 2.4263461398759394,
          "safety_factor": 33.68008049028071,
          "section_height_mm": 4.41623589050505,
          "stage_id": "input",
          "tangential_force_n": 27.027027027027028,
          "tooth_count": 37,
          "transmitted_torque_nm": 1.0
        },
        {
          "cumulative_mesh_efficiency": 0.95,
          "fillet_radius_mm": 0.2554334771906497,
          "max_von_mises_mpa": 21.62504729000021,
          "member": 0,
          "mesh_element_count": 240,
          "model_version": "involute-tooth-root-plane-stress-v3",
          "pressure_angle_deg": 20.0,
          "radial_force_n": 9.345181690618709,
          "root_width_mm": 2.4263461398759394,
          "safety_factor": 35.45271630555862,
          "section_height_mm": 4.41623589050505,
          "stage_id": "compound",
          "tangential_force_n": 25.675675675675677,
          "tooth_count": 37,
          "transmitted_torque_nm": 0.95
        },
        {
          "cumulative_mesh_efficiency": 0.95,
          "fillet_radius_mm": 0.2554334771906497,
          "max_von_mises_mpa": 21.62504729000021,
          "member": 1,
          "mesh_element_count": 240,
          "model_version": "involute-tooth-root-plane-stress-v3",
          "pressure_angle_deg": 20.0,
          "radial_force_n": 9.345181690618709,
          "root_width_mm": 2.4263461398759394,
          "safety_factor": 35.45271630555862,
          "section_height_mm": 4.41623589050505,
          "stage_id": "compound",
          "tangential_force_n": 25.675675675675677,
          "tooth_count": 37,
          "transmitted_torque_nm": 0.95
        },
        {
          "cumulative_mesh_efficiency": 0.9025,
          "fillet_radius_mm": 1.0238198171021402,
          "max_von_mises_mpa": 13.51611210930968,
          "member": 0,
          "mesh_element_count": 240,
          "model_version": "involute-tooth-root-plane-stress-v3",
          "pressure_angle_deg": 20.0,
          "radial_force_n": 8.877922606087772,
          "root_width_mm": 4.326534511097554,
          "safety_factor": 56.72242583269186,
          "section_height_mm": 4.361191140070961,
          "stage_id": "output",
          "tangential_force_n": 24.391891891891888,
          "tooth_count": 24,
          "transmitted_torque_nm": 0.5854054054054053
        }
      ],
      "valid": true
    },
    {
      "instance_id": "train-procedural-0015",
      "minimum_safety_factor": 4.22632283630041,
      "report_count": 4,
      "reports": [
        {
          "cumulative_mesh_efficiency": 1.0,
          "fillet_radius_mm": 0.5410662861939244,
          "max_von_mises_mpa": 97.2126691515072,
          "member": 0,
          "mesh_element_count": 240,
          "model_version": "involute-tooth-root-plane-stress-v3",
          "pressure_angle_deg": 20.0,
          "radial_force_n": 31.649585588365422,
          "root_width_mm": 2.2355227201024688,
          "safety_factor": 7.8864892133741,
          "section_height_mm": 2.1769652864909723,
          "stage_id": "input",
          "tangential_force_n": 86.95652173913044,
          "tooth_count": 23,
          "transmitted_torque_nm": 1.0
        },
        {
          "cumulative_mesh_efficiency": 0.95,
          "fillet_radius_mm": 0.2762987097914156,
          "max_von_mises_mpa": 111.28929111474724,
          "member": 0,
          "mesh_element_count": 240,
          "model_version": "involute-tooth-root-plane-stress-v3",
          "pressure_angle_deg": 20.0,
          "radial_force_n": 30.067106308947146,
          "root_width_mm": 1.5802857056892479,
          "safety_factor": 6.88895273738583,
          "section_height_mm": 2.2005141167778888,
          "stage_id": "compound",
          "tangential_force_n": 82.6086956521739,
          "tooth_count": 32,
          "transmitted_torque_nm": 1.3217391304347825
        },
        {
          "cumulative_mesh_efficiency": 0.95,
          "fillet_radius_mm": 0.6565882567746115,
          "max_von_mises_mpa": 119.52671665245651,
          "member": 1,
          "mesh_element_count": 240,
          "model_version": "involute-tooth-root-plane-stress-v3",
          "pressure_angle_deg": 20.0,
          "radial_force_n": 50.63933694138467,
          "root_width_mm": 2.5222110375037428,
          "safety_factor": 6.414186619848978,
          "section_height_mm": 2.157883893319852,
          "stage_id": "compound",
          "tangential_force_n": 139.1304347826087,
          "tooth_count": 19,
          "transmitted_torque_nm": 1.3217391304347825
        },
        {
          "cumulative_mesh_efficiency": 0.9025,
          "fillet_radius_mm": 0.30592039893479317,
          "max_von_mises_mpa": 181.40276934872836,
          "member": 0,
          "mesh_element_count": 240,
          "model_version": "involute-tooth-root-plane-stress-v3",
          "pressure_angle_deg": 20.0,
          "radial_force_n": 48.107370094315435,
          "root_width_mm": 1.6535126647090495,
          "safety_factor": 4.22632283630041,
          "section_height_mm": 2.198658427751784,
          "stage_id": "output",
          "tangential_force_n": 132.17391304347825,
          "tooth_count": 31,
          "transmitted_torque_nm": 2.048695652173913
        }
      ],
      "valid": true
    },
    {
      "instance_id": "train-procedural-0012",
      "minimum_safety_factor": 35.67599037450468,
      "report_count": 4,
      "reports": [
        {
          "cumulative_mesh_efficiency": 1.0,
          "fillet_radius_mm": 0.6,
          "max_von_mises_mpa": 21.489709426947083,
          "member": 0,
          "mesh_element_count": 240,
          "model_version": "involute-tooth-root-plane-stress-v3",
          "pressure_angle_deg": 20.0,
          "radial_force_n": 7.912396397091356,
          "root_width_mm": 2.91537077089227,
          "safety_factor": 35.67599037450468,
          "section_height_mm": 5.0429515026566705,
          "stage_id": "input",
          "tangential_force_n": 21.73913043478261,
          "tooth_count": 46,
          "transmitted_torque_nm": 1.0
        },
        {
          "cumulative_mesh_efficiency": 0.95,
          "fillet_radius_mm": 1.255812700559762,
          "max_von_mises_mpa": 9.322806002609711,
          "member": 0,
          "mesh_element_count": 240,
          "model_version": "involute-tooth-root-plane-stress-v3",
          "pressure_angle_deg": 20.0,
          "radial_force_n": 7.5167765772367865,
          "root_width_mm": 4.901921253366181,
          "safety_factor": 82.23561301737432,
          "section_height_mm": 4.326990558200347,
          "stage_id": "compound",
          "tangential_force_n": 20.652173913043477,
          "tooth_count": 20,
          "transmitted_torque_nm": 0.41304347826086957
        },
        {
          "cumulative_mesh_efficiency": 0.95,
          "fillet_radius_mm": 0.6,
          "max_von_mises_mpa": 8.962948920877855,
          "member": 1,
          "mesh_element_count": 240,
          "model_version": "involute-tooth-root-plane-stress-v3",
          "pressure_angle_deg": 20.0,
          "radial_force_n": 3.3407895898830167,
          "root_width_mm": 2.928819907197683,
          "safety_factor": 85.5373240921669,
          "section_height_mm": 5.041655184527713,
          "stage_id": "compound",
          "tangential_force_n": 9.178743961352657,
          "tooth_count": 45,
          "transmitted_torque_nm": 0.41304347826086957
        },
        {
          "cumulative_mesh_efficiency": 0.9025,
          "fillet_radius_mm": 0.6,
          "max_von_mises_mpa": 8.402239357561145,
          "member": 0,
          "mesh_element_count": 240,
          "model_version": "involute-tooth-root-plane-stress-v3",
          "pressure_angle_deg": 20.0,
          "radial_force_n": 3.173750110388866,
          "root_width_mm": 2.943577068562112,
          "safety_factor": 91.24551611074327,
          "section_height_mm": 5.040307795179288,
          "stage_id": "output",
          "tangential_force_n": 8.719806763285025,
          "tooth_count": 44,
          "transmitted_torque_nm": 0.3836714975845411
        }
      ],
      "valid": true
    },
    {
      "instance_id": "train-procedural-0014",
      "minimum_safety_factor": 19.727095911164252,
      "report_count": 4,
      "reports": [
        {
          "cumulative_mesh_efficiency": 1.0,
          "fillet_radius_mm": 0.44999999999999996,
          "max_von_mises_mpa": 38.86363558625896,
          "member": 0,
          "mesh_element_count": 240,
          "model_version": "involute-tooth-root-plane-stress-v3",
          "pressure_angle_deg": 20.0,
          "radial_force_n": 12.132341142206746,
          "root_width_mm": 2.2736302780492115,
          "safety_factor": 19.727095911164252,
          "section_height_mm": 3.7100933486223546,
          "stage_id": "input",
          "tangential_force_n": 33.333333333333336,
          "tooth_count": 40,
          "transmitted_torque_nm": 1.0
        },
        {
          "cumulative_mesh_efficiency": 0.95,
          "fillet_radius_mm": 1.0276515992190145,
          "max_von_mises_mpa": 18.538861567453655,
          "member": 0,
          "mesh_element_count": 240,
          "model_version": "involute-tooth-root-plane-stress-v3",
          "pressure_angle_deg": 20.0,
          "radial_force_n": 11.525724085096405,
          "root_width_mm": 3.8896503716824107,
          "safety_factor": 41.3545709846934,
          "section_height_mm": 3.2272970776721195,
          "stage_id": "compound",
          "tangential_force_n": 31.66666666666666,
          "tooth_count": 18,
          "transmitted_torque_nm": 0.42749999999999994
        },
        {
          "cumulative_mesh_efficiency": 0.95,
          "fillet_radius_mm": 0.9418595254198188,
          "max_von_mises_mpa": 17.15396304480268,
          "member": 1,
          "mesh_element_count": 240,
          "model_version": "involute-tooth-root-plane-stress-v3",
          "pressure_angle_deg": 20.0,
          "radial_force_n": 10.373151676586765,
          "root_width_mm": 3.67644094002463,
          "safety_factor": 44.69326794422306,
          "section_height_mm": 3.2452429186502663,
          "stage_id": "compound",
          "tangential_force_n": 28.499999999999996,
          "tooth_count": 20,
          "transmitted_torque_nm": 0.42749999999999994
        },
        {
          "cumulative_mesh_efficiency": 0.9025,
          "fillet_radius_mm": 0.5918028207215293,
          "max_von_mises_mpa": 23.433460788540735,
          "member": 0,
          "mesh_element_count": 240,
          "model_version": "involute-tooth-root-plane-stress-v3",
          "pressure_angle_deg": 20.0,
          "radial_force_n": 9.854494092757427,
          "root_width_mm": 2.809011727960755,
          "safety_factor": 32.71674950554365,
          "section_height_mm": 3.2882675943827238,
          "stage_id": "output",
          "tangential_force_n": 27.074999999999996,
          "tooth_count": 28,
          "transmitted_torque_nm": 0.5685749999999999
        }
      ],
      "valid": true
    },
    {
      "instance_id": "train-procedural-0013",
      "minimum_safety_factor": 28.19703102423018,
      "report_count": 4,
      "reports": [
        {
          "cumulative_mesh_efficiency": 1.0,
          "fillet_radius_mm": 0.7300859254296803,
          "max_von_mises_mpa": 24.019822426241262,
          "member": 0,
          "mesh_element_count": 240,
          "model_version": "involute-tooth-root-plane-stress-v3",
          "pressure_angle_deg": 20.0,
          "radial_force_n": 12.550697733317323,
          "root_width_mm": 3.599432307415903,
          "safety_factor": 31.918082201519354,
          "section_height_mm": 4.389016398065962,
          "stage_id": "input",
          "tangential_force_n": 34.48275862068966,
          "tooth_count": 29,
          "transmitted_torque_nm": 1.0
        },
        {
          "cumulative_mesh_efficiency": 0.95,
          "fillet_radius_mm": 0.19584615497068825,
          "max_von_mises_mpa": 27.189623829822974,
          "member": 0,
          "mesh_element_count": 240,
          "model_version": "involute-tooth-root-plane-stress-v3",
          "pressure_angle_deg": 20.0,
          "radial_force_n": 11.923162846651456,
          "root_width_mm": 2.2791829325053055,
          "safety_factor": 28.19703102423018,
          "section_height_mm": 4.418742812371434,
          "stage_id": "compound",
          "tangential_force_n": 32.758620689655174,
          "tooth_count": 38,
          "transmitted_torque_nm": 1.2448275862068965
        },
        {
          "cumulative_mesh_efficiency": 0.95,
          "fillet_radius_mm": 0.6,
          "max_von_mises_mpa": 26.750983114234106,
          "member": 1,
          "mesh_element_count": 240,
          "model_version": "involute-tooth-root-plane-stress-v3",
          "pressure_angle_deg": 20.0,
          "radial_force_n": 9.849569308103376,
          "root_width_mm": 2.91537077089227,
          "safety_factor": 28.659382849325112,
          "section_height_mm": 5.0429515026566705,
          "stage_id": "compound",
          "tangential_force_n": 27.061469265367315,
          "tooth_count": 46,
          "transmitted_torque_nm": 1.2448275862068965
        },
        {
          "cumulative_mesh_efficiency": 0.9025,
          "fillet_radius_mm": 0.9653392627532931,
          "max_von_mises_mpa": 14.01947673726952,
          "member": 0,
          "mesh_element_count": 240,
          "model_version": "involute-tooth-root-plane-stress-v3",
          "pressure_angle_deg": 20.0,
          "radial_force_n": 9.357090842698208,
          "root_width_mm": 4.181670980908751,
          "safety_factor": 54.68582608568779,
          "section_height_mm": 4.367784580856462,
          "stage_id": "output",
          "tangential_force_n": 25.70839580209895,
          "tooth_count": 25,
          "transmitted_torque_nm": 0.6427098950524737
        }
      ],
      "valid": true
    },
    {
      "instance_id": "test-tight-clearance-0004",
      "minimum_safety_factor": 35.60115512288158,
      "report_count": 4,
      "reports": [
        {
          "cumulative_mesh_efficiency": 1.0,
          "fillet_radius_mm": 0.49328325558212427,
          "max_von_mises_mpa": 21.53488177617907,
          "member": 0,
          "mesh_element_count": 240,
          "model_version": "involute-tooth-root-plane-stress-v3",
          "pressure_angle_deg": 20.0,
          "radial_force_n": 11.029401038369768,
          "root_width_mm": 3.0139710761548586,
          "safety_factor": 35.60115512288158,
          "section_height_mm": 4.40448628443351,
          "stage_id": "input",
          "tangential_force_n": 30.303030303030305,
          "tooth_count": 33,
          "transmitted_torque_nm": 1.0
        },
        {
          "cumulative_mesh_efficiency": 0.95,
          "fillet_radius_mm": 1.0238198171021402,
          "max_von_mises_mpa": 15.952030240652576,
          "member": 0,
          "mesh_element_count": 240,
          "model_version": "involute-tooth-root-plane-stress-v3",
          "pressure_angle_deg": 20.0,
          "radial_force_n": 10.477930986451279,
          "root_width_mm": 4.326534511097554,
          "safety_factor": 48.0607581041862,
          "section_height_mm": 4.361191140070961,
          "stage_id": "compound",
          "tangential_force_n": 28.787878787878785,
          "tooth_count": 24,
          "transmitted_torque_nm": 0.6909090909090909
        },
        {
          "cumulative_mesh_efficiency": 0.95,
          "fillet_radius_mm": 0.671006316199815,
          "max_von_mises_mpa": 15.978356653167541,
          "member": 1,
          "mesh_element_count": 240,
          "model_version": "involute-tooth-root-plane-stress-v3",
          "pressure_angle_deg": 20.0,
          "radial_force_n": 8.382344789161023,
          "root_width_mm": 3.453317950131114,
          "safety_factor": 47.981571779140566,
          "section_height_mm": 4.393323802168393,
          "stage_id": "compound",
          "tangential_force_n": 23.030303030303028,
          "tooth_count": 30,
          "transmitted_torque_nm": 0.6909090909090909
        },
        {
          "cumulative_mesh_efficiency": 0.9025,
          "fillet_radius_mm": 0.6,
          "max_von_mises_mpa": 20.772242590881817,
          "member": 0,
          "mesh_element_count": 240,
          "model_version": "involute-tooth-root-plane-stress-v3",
          "pressure_angle_deg": 20.0,
          "radial_force_n": 7.963227549702973,
          "root_width_mm": 2.9600015180277097,
          "safety_factor": 36.90822805060069,
          "section_height_mm": 5.038909620360386,
          "stage_id": "output",
          "tangential_force_n": 21.87878787878788,
          "tooth_count": 43,
          "transmitted_torque_nm": 0.9407878787878787
        }
      ],
      "valid": true
    },
    {
      "instance_id": "train-procedural-0019",
      "minimum_safety_factor": 18.60192585011445,
      "report_count": 4,
      "reports": [
        {
          "cumulative_mesh_efficiency": 1.0,
          "fillet_radius_mm": 0.5918028207215293,
          "max_von_mises_mpa": 41.21437064334656,
          "member": 0,
          "mesh_element_count": 240,
          "model_version": "involute-tooth-root-plane-stress-v3",
          "pressure_angle_deg": 20.0,
          "radial_force_n": 17.331915917438206,
          "root_width_mm": 2.809011727960755,
          "safety_factor": 18.60192585011445,
          "section_height_mm": 3.2882675943827238,
          "stage_id": "input",
          "tangential_force_n": 47.61904761904762,
          "tooth_count": 28,
          "transmitted_torque_nm": 1.0
        },
        {
          "cumulative_mesh_efficiency": 0.95,
          "fillet_radius_mm": 0.8551910064830857,
          "max_von_mises_mpa": 31.834431096006416,
          "member": 0,
          "mesh_element_count": 240,
          "model_version": "involute-tooth-root-plane-stress-v3",
          "pressure_angle_deg": 20.0,
          "radial_force_n": 16.465320121566297,
          "root_width_mm": 3.461365990472668,
          "safety_factor": 24.08293914078596,
          "section_height_mm": 3.259424299572057,
          "stage_id": "compound",
          "tangential_force_n": 45.23809523809524,
          "tooth_count": 22,
          "transmitted_torque_nm": 0.7464285714285714
        },
        {
          "cumulative_mesh_efficiency": 0.95,
          "fillet_radius_mm": 0.1468846162280144,
          "max_von_mises_mpa": 28.984093572965694,
          "member": 1,
          "mesh_element_count": 240,
          "model_version": "involute-tooth-root-plane-stress-v3",
          "pressure_angle_deg": 20.0,
          "radial_force_n": 9.532553754591014,
          "root_width_mm": 1.7093871993789755,
          "safety_factor": 26.451290075248682,
          "section_height_mm": 3.3140571092785684,
          "stage_id": "compound",
          "tangential_force_n": 26.19047619047619,
          "tooth_count": 38,
          "transmitted_torque_nm": 0.7464285714285714
        },
        {
          "cumulative_mesh_efficiency": 0.9025,
          "fillet_radius_mm": 0.19157510789298726,
          "max_von_mises_mpa": 27.940934117558854,
          "member": 0,
          "mesh_element_count": 240,
          "model_version": "involute-tooth-root-plane-stress-v3",
          "pressure_angle_deg": 20.0,
          "radial_force_n": 9.055926066861463,
          "root_width_mm": 1.8197596049069544,
          "safety_factor": 27.438834487100134,
          "section_height_mm": 3.31217691787878,
          "stage_id": "output",
          "tangential_force_n": 24.88095238095238,
          "tooth_count": 37,
          "transmitted_torque_nm": 0.6904464285714286
        }
      ],
      "valid": true
    },
    {
      "instance_id": "train-procedural-0016",
      "minimum_safety_factor": 3.7401177735336177,
      "report_count": 4,
      "reports": [
        {
          "cumulative_mesh_efficiency": 1.0,
          "fillet_radius_mm": 0.627906350279881,
          "max_von_mises_mpa": 90.28401602527298,
          "member": 0,
          "mesh_element_count": 240,
          "model_version": "involute-tooth-root-plane-stress-v3",
          "pressure_angle_deg": 20.0,
          "radial_force_n": 36.39702342662024,
          "root_width_mm": 2.4509606266830906,
          "safety_factor": 8.491720909402785,
          "section_height_mm": 2.1634952791001734,
          "stage_id": "input",
          "tangential_force_n": 100.0,
          "tooth_count": 20,
          "transmitted_torque_nm": 1.0
        },
        {
          "cumulative_mesh_efficiency": 0.95,
          "fillet_radius_mm": 0.24664162779106213,
          "max_von_mises_mpa": 135.02370873664302,
          "member": 0,
          "mesh_element_count": 240,
          "model_version": "involute-tooth-root-plane-stress-v3",
          "pressure_angle_deg": 20.0,
          "radial_force_n": 34.57717225528922,
          "root_width_mm": 1.5069855380774293,
          "safety_factor": 5.678015171113479,
          "section_height_mm": 2.202243142216755,
          "stage_id": "compound",
          "tangential_force_n": 95.0,
          "tooth_count": 33,
          "transmitted_torque_nm": 1.5675
        },
        {
          "cumulative_mesh_efficiency": 0.95,
          "fillet_radius_mm": 0.3945352138143523,
          "max_von_mises_mpa": 145.35793346275216,
          "member": 1,
          "mesh_element_count": 240,
          "model_version": "involute-tooth-root-plane-stress-v3",
          "pressure_angle_deg": 20.0,
          "radial_force_n": 40.75166730087658,
          "root_width_mm": 1.8726744853071688,
          "safety_factor": 5.274336586954329,
          "section_height_mm": 2.192178396255148,
          "stage_id": "compound",
          "tangential_force_n": 111.96428571428571,
          "tooth_count": 28,
          "transmitted_torque_nm": 1.5675
        },
        {
          "cumulative_mesh_efficiency": 0.9025,
          "fillet_radius_mm": 0.3,
          "max_von_mises_mpa": 204.98463232678614,
          "member": 0,
          "mesh_element_count": 240,
          "model_version": "involute-tooth-root-plane-stress-v3",
          "pressure_angle_deg": 20.0,
          "radial_force_n": 38.71408393583275,
          "root_width_mm": 1.471788534281056,
          "safety_factor": 3.7401177735336177,
          "section_height_mm": 2.520153897589644,
          "stage_id": "output",
          "tangential_force_n": 106.36607142857142,
          "tooth_count": 44,
          "transmitted_torque_nm": 2.3400535714285713
        }
      ],
      "valid": true
    },
    {
      "instance_id": "train-procedural-0018",
      "minimum_safety_factor": 19.494566568245904,
      "report_count": 4,
      "reports": [
        {
          "cumulative_mesh_efficiency": 1.0,
          "fillet_radius_mm": 0.44999999999999996,
          "max_von_mises_mpa": 39.32719734920735,
          "member": 0,
          "mesh_element_count": 240,
          "model_version": "involute-tooth-root-plane-stress-v3",
          "pressure_angle_deg": 20.0,
          "radial_force_n": 11.836430382640728,
          "root_width_mm": 2.252634363224348,
          "safety_factor": 19.494566568245904,
          "section_height_mm": 3.7564557216650982,
          "stage_id": "input",
          "tangential_force_n": 32.520325203252035,
          "tooth_count": 41,
          "transmitted_torque_nm": 1.0
        },
        {
          "cumulative_mesh_efficiency": 0.95,
          "fillet_radius_mm": 0.8115994292908866,
          "max_von_mises_mpa": 23.025439793609095,
          "member": 0,
          "mesh_element_count": 240,
          "model_version": "involute-tooth-root-plane-stress-v3",
          "pressure_angle_deg": 20.0,
          "radial_force_n": 11.244608863508692,
          "root_width_mm": 3.3532840801537027,
          "safety_factor": 33.29650480246034,
          "section_height_mm": 3.265447929736464,
          "stage_id": "compound",
          "tangential_force_n": 30.894308943089435,
          "tooth_count": 23,
          "transmitted_torque_nm": 0.5329268292682927
        },
        {
          "cumulative_mesh_efficiency": 0.95,
          "fillet_radius_mm": 1.0276515992190145,
          "max_von_mises_mpa": 23.110775937747153,
          "member": 1,
          "mesh_element_count": 240,
          "model_version": "involute-tooth-root-plane-stress-v3",
          "pressure_angle_deg": 20.0,
          "radial_force_n": 14.36811132559444,
          "root_width_mm": 3.8896503716824107,
          "safety_factor": 33.17355802902573,
          "section_height_mm": 3.2272970776721195,
          "stage_id": "compound",
          "tangential_force_n": 39.476061427280946,
          "tooth_count": 18,
          "transmitted_torque_nm": 0.5329268292682927
        },
        {
          "cumulative_mesh_efficiency": 0.9025,
          "fillet_radius_mm": 0.9848823851619173,
          "max_von_mises_mpa": 21.47875033160513,
          "member": 0,
          "mesh_element_count": 240,
          "model_version": "involute-tooth-root-plane-stress-v3",
          "pressure_angle_deg": 20.0,
          "radial_force_n": 13.649705759314717,
          "root_width_mm": 3.783316556255614,
          "safety_factor": 35.694193322716124,
          "section_height_mm": 3.2368258399797796,
          "stage_id": "output",
          "tangential_force_n": 37.502258355916894,
          "tooth_count": 19,
          "transmitted_torque_nm": 0.5344071815718158
        }
      ],
      "valid": true
    }
  ],
  "load_case": {
    "allowable_stress_mpa": 766.6666666666666,
    "efficiency": 0.95,
    "face_width_mm": 8.0,
    "input_torque_nm": 1.0,
    "material_name": "Toolox 44 (plate)",
    "poisson_ratio": 0.3,
    "youngs_modulus_mpa": 205000.0
  },
  "material": {
    "grade": "Toolox 44",
    "minimum_yield_strength_mpa": 1150.0,
    "poisson_ratio": 0.3,
    "product_form": "plate",
    "source_scope": "Guaranteed minimum 0.2% proof strength for plate, 6-130 mm.",
    "source_title": "SSAB: Toolox 44 product data",
    "source_url": "https://www.ssab.com/en-gb/brands-and-products/toolox/product-offer/toolox-44",
    "static_screen_factor": 1.5,
    "thickness_scope_mm": "6-130",
    "youngs_modulus_mpa": 205000.0
  },
  "median_safety_factor": 15.652359150932266,
  "minimum_safety_factor": 3.7401177735336177,
  "valid_fraction": 1.0
}
